placid_image_generator/__init__.py
placid_image_generator/generator.py
placid_image_generator-0.1.1.dist-info/METADATA
placid_image_generator-0.1.1.dist-info/WHEEL
placid_image_generator-0.1.1.dist-info/entry_points.txt
placid_image_generator-0.1.1.dist-info/top_level.txt
placid_image_generator-0.1.1.dist-info/RECORD
